siyuan_mcp_server/__init__.py
siyuan_mcp_server/tools.py
siyuan_mcp_server-0.22.0.dist-info/WHEEL
siyuan_mcp_server-0.22.0.dist-info/entry_points.txt
siyuan_mcp_server-0.22.0.dist-info/METADATA
siyuan_mcp_server-0.22.0.dist-info/RECORD
