Metadata-Version: 2.3
Name: siyuan-mcp-server
Version: 0.22.0
Summary: 思源笔记 MCP Server - 提供思源笔记API的MCP工具接口
Author: leolulu
Author-email: leolulu <348699103@qq.com>
License: MIT
Requires-Dist: mcp
Requires-Dist: requests
Requires-Dist: detect-secrets
Requires-Python: >=3.10
